LICENSE.txt
MANIFEST.in
README.rst
setup.cfg
setup.py
version.txt
docs/AUTHORS.txt
docs/HISTORY.rst
docs/INSTALL.rst
docs/LICENSE.GPL
vnccollab/__init__.py
vnccollab.zimbra.egg-info/PKG-INFO
vnccollab.zimbra.egg-info/SOURCES.txt
vnccollab.zimbra.egg-info/dependency_links.txt
vnccollab.zimbra.egg-info/entry_points.txt
vnccollab.zimbra.egg-info/namespace_packages.txt
vnccollab.zimbra.egg-info/not-zip-safe
vnccollab.zimbra.egg-info/requires.txt
vnccollab.zimbra.egg-info/top_level.txt
vnccollab/zimbra/__init__.py
vnccollab/zimbra/annotations.py
vnccollab/zimbra/config.py
vnccollab/zimbra/configure.zcml
vnccollab/zimbra/content.py
vnccollab/zimbra/interfaces.py
vnccollab/zimbra/overrides.zcml
vnccollab/zimbra/testing.py
vnccollab/zimbra/userdataschema.py
vnccollab/zimbra/util.py
vnccollab/zimbra/vocabularies.py
vnccollab/zimbra/zimbraclient.py
vnccollab/zimbra/browser/__init__.py
vnccollab/zimbra/browser/calendar.py
vnccollab/zimbra/browser/configure.zcml
vnccollab/zimbra/browser/json.py
vnccollab/zimbra/browser/mail.py
vnccollab/zimbra/browser/task.py
vnccollab/zimbra/browser/css/zimbra_mail_portlet.css
vnccollab/zimbra/browser/images/spinner_arrows.gif
vnccollab/zimbra/browser/js/zimbra_mail_portlet.js
vnccollab/zimbra/browser/templates/calendar.pt
vnccollab/zimbra/browser/templates/zimbra_emails_template.pt
vnccollab/zimbra/portlets/__init__.py
vnccollab/zimbra/portlets/configure.zcml
vnccollab/zimbra/portlets/zimbra_calendar.py
vnccollab/zimbra/portlets/zimbra_mail.py
vnccollab/zimbra/portlets/templates/zimbra_calendar.pt
vnccollab/zimbra/portlets/templates/zimbra_mail.pt
vnccollab/zimbra/profiles/default/browserlayer.xml
vnccollab/zimbra/profiles/default/cssregistry.xml
vnccollab/zimbra/profiles/default/jsregistry.xml
vnccollab/zimbra/profiles/default/memberdata_properties.xml
vnccollab/zimbra/profiles/default/metadata.xml
vnccollab/zimbra/profiles/default/portlets.xml
vnccollab/zimbra/profiles/default/registry.xml
vnccollab/zimbra/tests/__init__.py
vnccollab/zimbra/tests/base.py
vnccollab/zimbra/tests/mock_zimbra.py
vnccollab/zimbra/tests/test_content.py
vnccollab/zimbra/tests/test_install.py
vnccollab/zimbra/tests/test_portlets.py
vnccollab/zimbra/upgrades/__init__.py
vnccollab/zimbra/upgrades/configure.zcml
vnccollab/zimbra/upgrades/replaceportlets.py
