Metadata-Version: 1.1
Name: vnccollab.zimbra
Version: 1.0.8
Summary: VNC Collaboration Zimbra AddOn.
Home-page: https://github.com/vnc-biz/vnccollab.zimbra
Author: Jose Dinuncio
Author-email: jose.dinuncio@vnc.biz
License: gpl
Keywords: zimbra mail
Platform: UNKNOWN
Classifier: Environment :: Web Environment
Classifier: Framework :: Plone
Classifier: Programming Language :: Python
Classifier: Operating System :: OS Independent
